gdist.cp38-win_amd64.pyd
tvb_gdist-2.9.2.dist-info/LICENSE
tvb_gdist-2.9.2.dist-info/METADATA
tvb_gdist-2.9.2.dist-info/WHEEL
tvb_gdist-2.9.2.dist-info/top_level.txt
tvb_gdist-2.9.2.dist-info/RECORD
