Metadata-Version: 2.1
Name: tvb-gdist
Version: 2.9.2
Summary: Compute geodesic distances
Home-page: https://github.com/the-virtual-brain/tvb-gdist
Author: Danil Kirsanov, Gaurav Malhotra and Stuart Knock
Author-email: tvb.admin@thevirtualbrain.org
License: GPL v3
Keywords: gdist geodesic distance geo tvb
Platform: UNKNOWN
License-File: LICENSE
Requires-Dist: numpy
Requires-Dist: scipy
Requires-Dist: cython
